dbComm/__init__.py
dbComm/mongo.py
dbcomm-0.4.1.dist-info/licenses/LICENSE
dbcomm-0.4.1.dist-info/licenses/NOTICE
dbcomm-0.4.1.dist-info/METADATA
dbcomm-0.4.1.dist-info/WHEEL
dbcomm-0.4.1.dist-info/top_level.txt
dbcomm-0.4.1.dist-info/RECORD
