Metadata-Version: 2.4
Name: dbComm
Version: 0.4.1
Summary: Module for communicating with a (MongoDB) database
Author-email: Pigeon Caviness <pigeon@llnl.gov>
Project-URL: Homepage, https://github.com/LLNL/dbComm
Keywords: mongoDB,pymongo,database
Classifier: Programming Language :: Python :: 3
Classifier: License :: OSI Approved :: Python Software Foundation License
Classifier: Operating System :: OS Independent
Requires-Python: >=3.7
License-File: LICENSE
License-File: NOTICE
Requires-Dist: pymongo>=3.12.0
Requires-Dist: sshtunnel>=0.4.0
Dynamic: license-file
